buildfunctions/__init__.py
buildfunctions/api.py
buildfunctions-0.2.0.dist-info/METADATA
buildfunctions-0.2.0.dist-info/WHEEL
buildfunctions-0.2.0.dist-info/top_level.txt
buildfunctions-0.2.0.dist-info/RECORD
