Metadata-Version: 2.4
Name: buildfunctions
Version: 0.2.0
Summary: Python SDK
Classifier: Programming Language :: Python :: 3
Requires-Python: >=3.8
